bitoproClient/bitopro_indicator.py
bitoproClient/bitopro_restful_client.py
bitoproClient/bitopro_util.py
bitoproClient/bitopro_websocket_client.py
bitopro_client-1.0.6.dist-info/LICENSE
bitopro_client-1.0.6.dist-info/METADATA
bitopro_client-1.0.6.dist-info/WHEEL
bitopro_client-1.0.6.dist-info/top_level.txt
bitopro_client-1.0.6.dist-info/RECORD
