Metadata-Version: 2.1
Name: bitopro-client
Version: 1.0.6
Summary: For BitoPro crypto currency exchange written in Python
Home-page: https://github.com/bitoex/bitopro-api-python.git
Author: Bitoex
Author-email: support@bitopro.com
License: MIT
Classifier: Programming Language :: Python :: 3.9
Classifier: Programming Language :: Python :: 3.10
Classifier: Programming Language :: Python :: 3.11
Requires-Python: >=3.9
License-File: LICENSE
